mpiPython/__init__.py
mpiPython/__main__.py
mpiPython/check.py
mpiPython/lib/extension.h
mpiPython/lib/libcode.c
mpiPython/mpiPython/CWrap.py
mpiPython/mpiPython/__init__.py
mpiPython/mpiPython/betampiPython.py
mpiPython/mpiPython/mpiPython.py
mpiPython-1.0.14.dist-info/LICENSE
mpiPython-1.0.14.dist-info/METADATA
mpiPython-1.0.14.dist-info/WHEEL
mpiPython-1.0.14.dist-info/top_level.txt
mpiPython-1.0.14.dist-info/RECORD
