Metadata-Version: 2.1
Name: mpiPython
Version: 1.0.14
Summary: An MPI wrapper for Python
Author-email: Judah Nava <judah.nava@go.mnstate.edu>, Jaden Jinu Lee <jinu.lee@go.mnstate.edu>
License: Copyright 2024 Judah Nava
Keywords: mpi
Classifier: License :: OSI Approved :: Apache Software License
Classifier: Programming Language :: Python
Classifier: Programming Language :: Python :: 3
Requires-Python: >=3.10
License-File: LICENSE
Requires-Dist: setuptools
